src/units/pc/PC.v
// The PC Module is handling most Fetching Logic with help of control unit (sel_pc)
module PC(
  input         clk,     // Clock input
  input         rst,     // Reset input
  input         sel_pc,  // PC Select Control Signal
  input  [31:0] in_pc,   // input ALU
  input  [31:0] in_alu,  // input PC
  output [31:0] pc_nxt,  // Next
  output [31:0] pc       // Program Counter output
);

    reg [31:0] w_pc;
    reg [31:0] w_pc_nxt;

    assign pc = w_pc;
    assign pc_nxt = w_pc_nxt;

    always @(posedge clk or posedge rst) begin
        if (rst) begin
            w_pc <= 0;  // Reset the program counter to 0
            w_pc_nxt <=0;
        end else if (sel_pc) begin
            w_pc = in_alu;          // Increment the program counter if enabled
            w_pc_nxt = in_alu + 'd4;
        end else begin
            w_pc = in_pc;          // Increment the program counter if enabled
            w_pc_nxt = in_pc + 'd4;
        end
    end

endmodule

tb/pc_tb.v
module pc_tb;

    //reset that pulses once
    reg reset = 0;
    reg clk;
    reg sel_pc = 0;
    reg [31:0] in_alu = 32'h00008000;
    reg [31:0] in_pc_nxt;
    reg pc;
    
    PC c0 (
        .clk(clk),
        .rst(reset),
        .sel_pc(sel_pc),
        .in_pc(in_pc_nxt),
        .in_alu(in_alu),
        .pc_nxt(in_pc_nxt),
        .pc(pc)
    );

    initial begin 
        clk = 1'b0;
        forever #5 clk = ~clk;
    end

    initial begin

        $dumpfile("pc_tb.vcd");
        $dumpvars(0,pc_tb);

        # 10 reset = 1'b1;
        # 12 reset = 1'b0;
        # 50 sel_pc = 1'b0; 
        # 200 $finish;
    end

endmodule

scripts/pc_tb.vcd
$date
	Sun Nov 12 18:18:27 2023
$end
$version
	Icarus Verilog
$end
$timescale
	1s
$end
$scope module pc_tb $end
$var wire 1 ! pc $end
$var wire 32 " in_pc_nxt [31:0] $end
$var reg 1 # clk $end
$var reg 32 $ in_alu [31:0] $end
$var reg 1 % reset $end
$var reg 1 & sel_pc $end
$scope module c0 $end
$var wire 1 # clk $end
$var wire 32 ' in_alu [31:0] $end
$var wire 32 ( in_pc [31:0] $end
$var wire 32 ) pc_nxt [31:0] $end
$var wire 1 % rst $end
$var wire 1 & sel_pc $end
$var wire 32 * pc [31:0] $end
$var reg 32 + w_pc [31:0] $end
$var reg 32 , w_pc_nxt [31:0] $end
$upscope $end
$upscope $end
$enddefinitions $end
#0
$dumpvars
bx ,
bx +
bx *
bx )
bx (
b1000000000000000 '
0&
0%
b1000000000000000 $
0#
bx "
x!
$end
#5
1#
#10
0!
b0 "
b0 (
b0 )
b0 ,
b0 *
b0 +
0#
1%
#15
1#
#20
0#
#22
0%
#25
b100 "
b100 (
b100 )
b100 ,
1#
#30
0#
#35
b1000 "
b1000 (
b1000 )
b1000 ,
b100 *
b100 +
1#
#40
0#
#45
b1100 "
b1100 (
b1100 )
b1100 ,
b1000 *
b1000 +
1#
#50
0#
#55
b10000 "
b10000 (
b10000 )
b10000 ,
b1100 *
b1100 +
1#
#60
0#
#65
b10100 "
b10100 (
b10100 )
b10100 ,
b10000 *
b10000 +
1#
#70
0#
#75
b11000 "
b11000 (
b11000 )
b11000 ,
b10100 *
b10100 +
1#
#80
0#
#85
b11100 "
b11100 (
b11100 )
b11100 ,
b11000 *
b11000 +
1#
#90
0#
#95
b100000 "
b100000 (
b100000 )
b100000 ,
b11100 *
b11100 +
1#
#100
0#
#105
b100100 "
b100100 (
b100100 )
b100100 ,
b100000 *
b100000 +
1#
#110
0#
#115
b101000 "
b101000 (
b101000 )
b101000 ,
b100100 *
b100100 +
1#
#120
0#
#125
b101100 "
b101100 (
b101100 )
b101100 ,
b101000 *
b101000 +
1#
#130
0#
#135
b110000 "
b110000 (
b110000 )
b110000 ,
b101100 *
b101100 +
1#
#140
0#
#145
b110100 "
b110100 (
b110100 )
b110100 ,
b110000 *
b110000 +
1#
#150
0#
#155
b111000 "
b111000 (
b111000 )
b111000 ,
b110100 *
b110100 +
1#
#160
0#
#165
b111100 "
b111100 (
b111100 )
b111100 ,
b111000 *
b111000 +
1#
#170
0#
#175
b1000000 "
b1000000 (
b1000000 )
b1000000 ,
b111100 *
b111100 +
1#
#180
0#
#185
b1000100 "
b1000100 (
b1000100 )
b1000100 ,
b1000000 *
b1000000 +
1#
#190
0#
#195
b1001000 "
b1001000 (
b1001000 )
b1001000 ,
b1000100 *
b1000100 +
1#
#200
0#
#205
b1001100 "
b1001100 (
b1001100 )
b1001100 ,
b1001000 *
b1001000 +
1#
#210
0#
#215
b1010000 "
b1010000 (
b1010000 )
b1010000 ,
b1001100 *
b1001100 +
1#
#220
0#
#225
b1010100 "
b1010100 (
b1010100 )
b1010100 ,
b1010000 *
b1010000 +
1#
#230
0#
#235
b1011000 "
b1011000 (
b1011000 )
b1011000 ,
b1010100 *
b1010100 +
1#
#240
0#
#245
b1011100 "
b1011100 (
b1011100 )
b1011100 ,
b1011000 *
b1011000 +
1#
#250
0#
#255
b1100000 "
b1100000 (
b1100000 )
b1100000 ,
b1011100 *
b1011100 +
1#
#260
0#
#265
b1100100 "
b1100100 (
b1100100 )
b1100100 ,
b1100000 *
b1100000 +
1#
